GPmix/__init__.py
GPmix/misc.py
GPmix/projector.py
GPmix/smoother.py
GPmix/unigmm.py
gpmix-0.1.6.dist-info/licenses/LICENSE
gpmix-0.1.6.dist-info/METADATA
gpmix-0.1.6.dist-info/WHEEL
gpmix-0.1.6.dist-info/top_level.txt
gpmix-0.1.6.dist-info/RECORD
