Metadata-Version: 2.4
Name: GPmix
Version: 0.1.6
Summary: GPmix is an ensemble clustering algorithm for functional data via random projections.
Author: Emmanuel Akeweje and Mimi Zhang
Author-email: eakeweje@tcd.ie
License: MIT
Project-URL: Documentation, https://gpmix.readthedocs.io/en/latest/
Project-URL: Source, https://github.com/EAkeweje/GPmix
Project-URL: Issues, https://github.com/EAkeweje/GPmix/issues
Classifier: Programming Language :: Python :: 3
Classifier: Operating System :: OS Independent
Requires-Python: >=3.9
License-File: LICENSE
Requires-Dist: joblib>=1.2.0
Requires-Dist: matplotlib>=3.6.3
Requires-Dist: numpy>=1.26.2
Requires-Dist: PyWavelets>=1.4.1
Requires-Dist: scikit_fda>=0.10.1
Requires-Dist: scikit_learn>=1.2.2
Requires-Dist: scipy>=1.11.4
Requires-Dist: seaborn>=0.13.0
Dynamic: author
Dynamic: author-email
Dynamic: classifier
Dynamic: description
Dynamic: description-content-type
Dynamic: license
Dynamic: license-file
Dynamic: project-url
Dynamic: requires-dist
Dynamic: requires-python
Dynamic: summary
